[
	{
		"name": "Odoo Development Training",
		"whoIssue": "Arkana Solusi Digital, PT",
		"issuedAt": "Issued May 2023",
		"credentialsId": "KXAG796M386P",
		"certificationURL": "https://drive.google.com/file/d/17riMapZsRpwU1f0XNWB5URL0spf_DLaE/view?usp=sharing"
	},
	{
		"name": "Python Certificate",
		"whoIssue": "HackerRank",
		"issuedAt": "Issued Dec 2022",
		"credentialsId": "cf16fb2d03e3",
		"certificationURL": "https://www.hackerrank.com/certificates/cf16fb2d03e3"
	},
	{
		"name": "SQL (Basic) Certificate",
		"whoIssue": "HackerRank",
		"issuedAt": "Issued Dec 2022",
		"credentialsId": "d37495a42b6e",
		"certificationURL": "https://www.hackerrank.com/certificates/d37495a42b6e"
	},
	{
		"name": "SQL (Intermediate) Certificate",
		"whoIssue": "HackerRank",
		"issuedAt": "Issued Dec 2022",
		"credentialsId": "04dfb65b7cfd",
		"certificationURL": "https://www.hackerrank.com/certificates/04dfb65b7cfd"
	},
	{
		"name": "Belajar Membuat Aplikasi Back-End untuk Pemula",
		"whoIssue": "Dicoding Academy",
		"issuedAt": "Issued Aug 2022",
		"credentialsId": "EYX49KV7WPDL",
		"certificationURL": "https://www.dicoding.com/certificates/EYX49KV7WPDL"
	},
	{
		"name": "Belajar Dasar Pemrograman JavaScript",
		"whoIssue": "Dicoding Academy",
		"issuedAt": "Issued Jun 2022",
		"credentialsId": "ERZR021MWXYV",
		"certificationURL": "https://www.dicoding.com/certificates/ERZR021MWXYV"
	},
	{
		"name": "Laravel Web Development ",
		"whoIssue": "SanberCode",
		"issuedAt": "Issued Feb 2022",
		"credentialsId": "7eec2b7e-18a5-4882-bb44-2d1c6ab63643",
		"certificationURL": "https://sanbercode.com/sertifikat/generate/7eec2b7e-18a5-4882-bb44-2d1c6ab63643"
	},
	{
		"name": "Data Cleaning",
		"whoIssue": "Kaggle",
		"issuedAt": "Issued Sep 2021",
		"credentialsId": "data-cleaning",
		"certificationURL": "https://www.kaggle.com/learn/certification/emnopal/data-cleaning"
	},
	{
		"name": "Feature Engineering",
		"whoIssue": "Kaggle",
		"issuedAt": "Issued Sep 2021",
		"credentialsId": "feature-engineering",
		"certificationURL": "https://www.kaggle.com/learn/certification/emnopal/feature-engineering"
	},
	{
		"name": "Geospatial Analysis",
		"whoIssue": "Kaggle",
		"issuedAt": "Issued Sep 2021",
		"credentialsId": "geospatial-analysis",
		"certificationURL": "https://www.kaggle.com/learn/certification/emnopal/geospatial-analysis"
	},
	{
		"name": "Intermediate Machine Learning",
		"whoIssue": "Kaggle",
		"issuedAt": "Issued Sep 2021",
		"credentialsId": "intermediate-machine-learning",
		"certificationURL": "https://www.kaggle.com/learn/certification/emnopal/intermediate-machine-learning"
	},
	{
		"name": "Intro to BigQuery SQL",
		"whoIssue": "Kaggle",
		"issuedAt": "Issued Sep 2021",
		"credentialsId": "intro-to-sql",
		"certificationURL": "https://www.kaggle.com/learn/certification/emnopal/intro-to-sql"
	},
	{
		"name": "Pandas",
		"whoIssue": "Kaggle",
		"issuedAt": "Issued Sep 2021",
		"credentialsId": "pandas",
		"certificationURL": "https://www.kaggle.com/learn/certification/emnopal/pandas"
	},
	{
		"name": "TensorFlow Developer Certification",
		"whoIssue": "Google",
		"issuedAt": "Issued Sep 2021 · Expires Sep 2024",
		"credentialsId": "38354960",
		"certificationURL": "https://api.accredible.com/v1/auth/invite?code=20a91057a48d44e9dc6e&credential_id=f8a34cce-567d-478e-94f8-105d7dac2433&url=https%3A%2F%2Fwww.credential.net%2Ff8a34cce-567d-478e-94f8-105d7dac2433&ident=ece51e58bd61a5637332b442c109b72aabb16f47"
	},
	{
		"name": "Time Series",
		"whoIssue": "Kaggle",
		"issuedAt": "Issued Sep 2021",
		"credentialsId": "time-series",
		"certificationURL": "https://www.kaggle.com/learn/certification/emnopal/time-series"
	},
	{
		"name": "Huawei - Artificial Intelligence",
		"whoIssue": "Kementerian Komunikasi dan Informatika Republik Indonesia",
		"issuedAt": "Issued Aug 2021",
		"credentialsId": "011242118121-14/DTS/BLSDM.KOMINF0/10/2021",
		"certificationURL": "https://drive.google.com/file/d/1Wrq_OemLmhoXuUhbCr48CE5DJPkyHzLQ/view?usp=sharing"
	},
	{
		"name": "Intro to Machine Learning",
		"whoIssue": "Kaggle",
		"issuedAt": "Issued Aug 2021",
		"credentialsId": "intro-to-machine-learning",
		"certificationURL": "https://www.kaggle.com/learn/certification/emnopal/intro-to-machine-learning"
	},
	{
		"name": "Belajar Dasar Visualisasi Data",
		"whoIssue": "Dicoding Academy",
		"issuedAt": "Issued Jul 2021",
		"credentialsId": "98XW63DVLXM3",
		"certificationURL": "https://www.dicoding.com/certificates/98XW63DVLXM3"
	},
	{
		"name": "Memulai Pemrograman Dengan Java",
		"whoIssue": "Dicoding Academy",
		"issuedAt": "Issued Jul 2021",
		"credentialsId": "RVZK19M3NPD5",
		"certificationURL": "https://www.dicoding.com/certificates/RVZK19M3NPD5"
	},
	{
		"name": " Cloud Practitioner Essentials (Belajar Dasar AWS Cloud)",
		"whoIssue": "Dicoding Academy",
		"issuedAt": "Issued Jun 2021",
		"credentialsId": "ERZR531YMPYV",
		"certificationURL": "https://www.dicoding.com/certificates/ERZR531YMPYV"
	},
	{
		"name": "Belajar Machine Learning untuk Pemula",
		"whoIssue": "Dicoding Academy",
		"issuedAt": "Issued Jun 2021",
		"credentialsId": "0LZ0DKE2NX65",
		"certificationURL": "https://www.dicoding.com/certificates/0LZ0DKE2NX65"
	},
	{
		"name": "Memulai Pemrograman Dengan Python",
		"whoIssue": "Dicoding Academy",
		"issuedAt": "Issued Jun 2021",
		"credentialsId": "53XEE2NKRXRN",
		"certificationURL": "https://www.dicoding.com/certificates/53XEE2NKRXRN"
	},
	{
		"name": "DeepLearning.AI TensorFlow Developer",
		"whoIssue": "DeepLearning.AI",
		"issuedAt": "Issued Apr 2021",
		"credentialsId": "CA4PWYK449Q5",
		"certificationURL": "https://www.coursera.org/account/accomplishments/professional-cert/CA4PWYK449Q5"
	},
	{
		"name": "Structuring Machine Learning Projects",
		"whoIssue": "DeepLearning.AI",
		"issuedAt": "Issued Apr 2021",
		"credentialsId": "FAKVGWZBXNJX",
		"certificationURL": "https://www.coursera.org/account/accomplishments/verify/FAKVGWZBXNJX"
	},
	{
		"name": "TensorFlow: Data and Deployment",
		"whoIssue": "DeepLearning.AI",
		"issuedAt": "Issued Apr 2021",
		"credentialsId": "LSA6E8NQKK7B",
		"certificationURL": "https://www.coursera.org/account/accomplishments/specialization/LSA6E8NQKK7B"
	},
	{
		"name": "Google IT Automation with Python Professional Certificate",
		"whoIssue": "Google",
		"issuedAt": "Issued Mar 2021",
		"credentialsId": "BDYKTLRAZRRC",
		"certificationURL": "https://www.coursera.org/account/accomplishments/professional-cert/BDYKTLRAZRRC"
	},
	{
		"name": "Mathematics for Machine Learning",
		"whoIssue": "Imperial College London",
		"issuedAt": "Issued Mar 2021",
		"credentialsId": "69KZZLWAMCS6",
		"certificationURL": "https://www.coursera.org/account/accomplishments/specialization/69KZZLWAMCS6"
	},
	{
		"name": "Google IT Support",
		"whoIssue": "Google",
		"issuedAt": "Issued Feb 2021",
		"credentialsId": "3TGEJ6NJQSEP",
		"certificationURL": "https://www.coursera.org/account/accomplishments/professional-cert/3TGEJ6NJQSEP"
	}
]
